gtm_healthcheck_automation/__init__.py
gtm_healthcheck_automation/gtm_size.py
gtm_healthcheck-0.1.1.dist-info/METADATA
gtm_healthcheck-0.1.1.dist-info/WHEEL
gtm_healthcheck-0.1.1.dist-info/entry_points.txt
gtm_healthcheck-0.1.1.dist-info/top_level.txt
gtm_healthcheck-0.1.1.dist-info/RECORD
