Metadata-Version: 2.1
Name: gtm-healthcheck
Version: 0.1.1
Summary: Generic tool to calculate size of each tag, trigger and variable assimilated in a GTM container
Home-page: https://www.webengage.com/
Author: Nipun Patel
Author-email: nipunp27@gmail.com
License: MIT
Classifier: Programming Language :: Python :: 3
Classifier: License :: OSI Approved :: MIT License
Classifier: Operating System :: OS Independent
Requires-Python: >=3.6
